dbinfer_relbench_adapter/__init__.py
dbinfer_relbench_adapter/adapters.py
dbinfer_relbench_adapter/cache.py
dbinfer_relbench_adapter/loader.py
dbinfer_relbench_adapter-0.1.3.dist-info/licenses/LICENSE
dbinfer_relbench_adapter-0.1.3.dist-info/METADATA
dbinfer_relbench_adapter-0.1.3.dist-info/WHEEL
dbinfer_relbench_adapter-0.1.3.dist-info/top_level.txt
dbinfer_relbench_adapter-0.1.3.dist-info/RECORD
